xformer/__init__.py
xformer/cell.py
xformer/test_cell.py
xformer/test_transformer.py
xformer/transformer.py
xformer-1.0.1.dist-info/DESCRIPTION.rst
xformer-1.0.1.dist-info/METADATA
xformer-1.0.1.dist-info/RECORD
xformer-1.0.1.dist-info/WHEEL
xformer-1.0.1.dist-info/metadata.json
xformer-1.0.1.dist-info/top_level.txt
